mmapy/__init__.py
mmapy/mma.py
mmapy-0.3.1.dist-info/LICENSE
mmapy-0.3.1.dist-info/METADATA
mmapy-0.3.1.dist-info/WHEEL
mmapy-0.3.1.dist-info/top_level.txt
mmapy-0.3.1.dist-info/RECORD
