Metadata-Version: 2.1
Name: mmapy
Version: 0.3.1
Summary: Python implementation of the Method of Moving Asymptotes (MMA).
Author-email: Arjen Deetman <info@arjendeetman.nl>
License: GNU General Public License v3 (GPLv3)
Project-URL: Homepage, https://github.com/arjendeetman/GCMMA-MMA-Python
Project-URL: Source, https://github.com/arjendeetman/GCMMA-MMA-Python
Project-URL: Issues, https://github.com/arjendeetman/GCMMA-MMA-Python/issues
Classifier: License :: OSI Approved :: GNU General Public License v3 (GPLv3)
Classifier: Intended Audience :: Science/Research
Classifier: Topic :: Scientific/Engineering
Classifier: Operating System :: OS Independent
Classifier: Programming Language :: Python
Classifier: Programming Language :: Python :: 3
Classifier: Programming Language :: Python :: 3.8
Classifier: Programming Language :: Python :: 3.9
Classifier: Programming Language :: Python :: 3.10
Classifier: Programming Language :: Python :: 3.11
Classifier: Programming Language :: Python :: 3.12
Classifier: Programming Language :: Python :: 3.13
Classifier: Programming Language :: Python :: 3 :: Only
Classifier: Programming Language :: Python :: Implementation :: CPython
Requires-Python: >=3.6
License-File: LICENSE
Requires-Dist: numpy
Requires-Dist: scipy
